LICENSE
LONG_DESCRIPTION.rst
MANIFEST.in
VERSION
setup.cfg
setup.py
svb/__init__.py
svb/api_requestor.py
svb/error.py
svb/http_client.py
svb/multipart_data_generator.py
svb/resource.py
svb/six.py
svb/util.py
svb/version.py
svb.egg-info/PKG-INFO
svb.egg-info/SOURCES.txt
svb.egg-info/dependency_links.txt
svb.egg-info/requires.txt
svb.egg-info/top_level.txt
svb/data/ca-certificates.crt
svb/test/__init__.py
svb/test/resources/__init__.py